README.md
pyproject.toml
setup.py
src/meteoFrance_data.egg-info/PKG-INFO
src/meteoFrance_data.egg-info/SOURCES.txt
src/meteoFrance_data.egg-info/dependency_links.txt
src/meteoFrance_data.egg-info/requires.txt
src/meteoFrance_data.egg-info/top_level.txt
src/meteofrance_data/__init__.py
src/meteofrance_data/__main__.py
src/meteofrance_data/client.py
src/meteofrance_data/const.py
src/meteofrance_data/exceptions.py
src/meteofrance_data/helpers.py
src/meteofrance_data/session.py
src/meteofrance_data/model/__init__.py
src/meteofrance_data/model/dictionary.py
src/meteofrance_data/model/forecast.py
src/meteofrance_data/model/observation.py
src/meteofrance_data/model/picture_of_the_day.py
src/meteofrance_data/model/place.py
src/meteofrance_data/model/rain.py
src/meteofrance_data/model/warning.py