Metadata-Version: 2.1
Name: meteoFrance-data
Version: 1.1.1
Summary: Un paquet des requêtes des données ouvertes de meteo-france
Author: Taoufik Bannour
Author-email: taoufik.bannour.ext@suez.com
Keywords: meteo,france,pypi,package
Classifier: Intended Audience :: Developers
Classifier: Programming Language :: Python :: 3.7
Classifier: Operating System :: OS Independent
Requires-Python: >=3.7
Provides-Extra: dev
